Metadata-Version: 2.1
Name: cserpent
Version: 1.1.3
License-File: LICENSE
Requires-Dist: numpy
